{"1":[{"arabic":"سَبَّحَ","transliteration":"","translation":""},{"arabic":"لِلّٰهِ","transliteration":"","translation":""},{"arabic":"مَا","transliteration":"","translation":""},{"arabic":"فِى","transliteration":"","translation":""},{"arabic":"السَّمٰوٰتِ","transliteration":"","translation":""},{"arabic":"وَمَا","transliteration":"","translation":""},{"arabic":"فِى","transliteration":"","translation":""},{"arabic":"الۡاَرۡضِۚ","transliteration":"","translation":""},{"arabic":"","transliteration":"","translation":""},{"arabic":"وَهُوَ","transliteration":"","translation":""},{"arabic":"الۡعَزِيۡزُ","transliteration":"","translation":""},{"arabic":"الۡحَكِيۡمُ","transliteration":"","translation":""}],"2":[{"arabic":"هُوَ","transliteration":"","translation":""},{"arabic":"الَّذِىۡۤ","transliteration":"","translation":""},{"arabic":"اَخۡرَجَ","transliteration":"","translation":""},{"arabic":"الَّذِيۡنَ","transliteration":"","translation":""},{"arabic":"كَفَرُوۡا","transliteration":"","translation":""},{"arabic":"مِنۡ","transliteration":"","translation":""},{"arabic":"اَهۡلِ","transliteration":"","translation":""},{"arabic":"الۡكِتٰبِ","transliteration":"","translation":""},{"arabic":"مِنۡ","transliteration":"","translation":""},{"arabic":"دِيَارِهِمۡ","transliteration":"","translation":""},{"arabic":"لِاَوَّلِ","transliteration":"","translation":""},{"arabic":"الۡحَشۡرِ​ؔؕ","transliteration":"","translation":""},{"arabic":"","transliteration":"","translation":""},{"arabic":"مَا","transliteration":"","translation":""},{"arabic":"ظَنَنۡـتُمۡ","transliteration":"","translation":""},{"arabic":"اَنۡ","transliteration":"","translation":""},{"arabic":"يَّخۡرُجُوۡا​","transliteration":"","translation":""},{"arabic":"","transliteration":"","translation":""},{"arabic":"وَظَنُّوۡۤا","transliteration":"","translation":""},{"arabic":"اَنَّهُمۡ","transliteration":"","translation":""},{"arabic":"مَّانِعَتُهُمۡ","transliteration":"","translation":""},{"arabic":"حُصُوۡنُهُمۡ","transliteration":"","translation":""},{"arabic":"مِّنَ","transliteration":"","translation":""},{"arabic":"اللّٰهِ","transliteration":"","translation":""},{"arabic":"فَاَتٰٮهُمُ","transliteration":"","translation":""},{"arabic":"اللّٰهُ","transliteration":"","translation":""},{"arabic":"مِنۡ","transliteration":"","translation":""},{"arabic":"حَيۡثُ","transliteration":"","translation":""},{"arabic":"لَمۡ","transliteration":"","translation":""},{"arabic":"يَحۡتَسِبُوۡا","transliteration":"","translation":""},{"arabic":"","transliteration":"","translation":""},{"arabic":"وَقَذَفَ","transliteration":"","translation":""},{"arabic":"فِىۡ","transliteration":"","translation":""},{"arabic":"قُلُوۡبِهِمُ","transliteration":"","translation":""},{"arabic":"الرُّعۡبَ","transliteration":"","translation":""},{"arabic":"","transliteration":"","translation":""},{"arabic":"يُخۡرِبُوۡنَ","transliteration":"","translation":""},{"arabic":"بُيُوۡتَهُمۡ","transliteration":"","translation":""},{"arabic":"بِاَيۡدِيۡهِمۡ","transliteration":"","translation":""},{"arabic":"وَاَيۡدِى","transliteration":"","translation":""},{"arabic":"الۡمُؤۡمِنِيۡنَ","transliteration":"","translation":""},{"arabic":"فَاعۡتَبِـرُوۡا","transliteration":"","translation":""},{"arabic":"يٰۤاُولِى","transliteration":"","translation":""},{"arabic":"الۡاَبۡصَارِ​","transliteration":"","translation":""}],"3":[{"arabic":"وَلَوۡلَاۤ","transliteration":"","translation":""},{"arabic":"اَنۡ","transliteration":"","translation":""},{"arabic":"كَتَبَ","transliteration":"","translation":""},{"arabic":"اللّٰهُ","transliteration":"","translation":""},{"arabic":"عَلَيۡهِمُ","transliteration":"","translation":""},{"arabic":"الۡجَـلَاۤءَ","transliteration":"","translation":""},{"arabic":"لَعَذَّبَهُمۡ","transliteration":"","translation":""},{"arabic":"فِى","transliteration":"","translation":""},{"arabic":"الدُّنۡيَا​ؕ","transliteration":"","translation":""},{"arabic":"","transliteration":"","translation":""},{"arabic":"وَلَهُمۡ","transliteration":"","translation":""},{"arabic":"فِى","transliteration":"","translation":""},{"arabic":"الۡاٰخِرَةِ","transliteration":"","translation":""},{"arabic":"عَذَابُ","transliteration":"","translation":""},{"arabic":"النَّارِ","transliteration":"","translation":""}],"4":[{"arabic":"ذٰ","transliteration":"","translation":""},{"arabic":"لِكَ","transliteration":"","translation":""},{"arabic":"بِاَنَّهُمۡ","transliteration":"","translation":""},{"arabic":"شَآقُّوا","transliteration":"","translation":""},{"arabic":"اللّٰهَ","transliteration":"","translation":""},{"arabic":"","transliteration":"","translation":""},{"arabic":"وَرَسُوۡلَهٗ​ ۚ","transliteration":"","translation":""},{"arabic":"وَمَنۡ","transliteration":"","translation":""},{"arabic":"يُّشَآقِّ","transliteration":"","translation":""},{"arabic":"اللّٰهَ","transliteration":"","translation":""},{"arabic":"فَاِنَّ","transliteration":"","translation":""},{"arabic":"اللّٰهَ","transliteration":"","translation":""},{"arabic":"شَدِيۡدُ الۡعِقَابِ","transliteration":"","translation":""}],"5":[{"arabic":"مَا","transliteration":"","translation":""},{"arabic":"قَطَعۡتُمۡ","transliteration":"","translation":""},{"arabic":"مِّنۡ","transliteration":"","translation":""},{"arabic":"لِّيۡنَةٍ","transliteration":"","translation":""},{"arabic":"اَوۡ","transliteration":"","translation":""},{"arabic":"تَرَكۡتُمُوۡهَا","transliteration":"","translation":""},{"arabic":"قَآٮِٕمَةً","transliteration":"","translation":""},{"arabic":"عَلٰٓى","transliteration":"","translation":""},{"arabic":"اُصُوۡلِهَا","transliteration":"","translation":""},{"arabic":"فَبِاِذۡنِ","transliteration":"","translation":""},{"arabic":"اللّٰهِ","transliteration":"","translation":""},{"arabic":"وَلِيُخۡزِىَ","transliteration":"","translation":""},{"arabic":"الۡفٰسِقِيۡنَ","transliteration":"","translation":""}],"6":[{"arabic":"وَمَاۤ","transliteration":"","translation":""},{"arabic":"اَفَآءَ","transliteration":"","translation":""},{"arabic":"اللّٰهُ","transliteration":"","translation":""},{"arabic":"عَلٰى","transliteration":"","translation":""},{"arabic":"رَسُوۡلِهٖ","transliteration":"","translation":""},{"arabic":"مِنۡهُمۡ","transliteration":"","translation":""},{"arabic":"فَمَاۤ","transliteration":"","translation":""},{"arabic":"اَوۡجَفۡتُمۡ","transliteration":"","translation":""},{"arabic":"عَلَيۡهِ","transliteration":"","translation":""},{"arabic":"مِنۡ","transliteration":"","translation":""},{"arabic":"خَيۡلٍ","transliteration":"","translation":""},{"arabic":"وَّلَا","transliteration":"","translation":""},{"arabic":"رِكَابٍ","transliteration":"","translation":""},{"arabic":"وَّلٰڪِنَّ","transliteration":"","translation":""},{"arabic":"اللّٰهَ","transliteration":"","translation":""},{"arabic":"يُسَلِّطُ","transliteration":"","translation":""},{"arabic":"رُسُلَهٗ","transliteration":"","translation":""},{"arabic":"عَلٰى","transliteration":"","translation":""},{"arabic":"مَنۡ","transliteration":"","translation":""},{"arabic":"يَّشَآءُ ​ؕ","transliteration":"","translation":""},{"arabic":"","transliteration":"","translation":""},{"arabic":"وَاللّٰهُ","transliteration":"","translation":""},{"arabic":"عَلٰى","transliteration":"","translation":""},{"arabic":"كُلِّ","transliteration":"","translation":""},{"arabic":"شَىۡءٍ","transliteration":"","translation":""},{"arabic":"قَدِيۡرٌ","transliteration":"","translation":""}],"7":[{"arabic":"مَاۤ","transliteration":"","translation":""},{"arabic":"اَفَآءَ","transliteration":"","translation":""},{"arabic":"اللّٰهُ","transliteration":"","translation":""},{"arabic":"عَلٰى","transliteration":"","translation":""},{"arabic":"رَسُوۡلِهٖ","transliteration":"","translation":""},{"arabic":"مِنۡ","transliteration":"","translation":""},{"arabic":"اَهۡلِ","transliteration":"","translation":""},{"arabic":"الۡقُرٰى","transliteration":"","translation":""},{"arabic":"فَلِلّٰهِ","transliteration":"","translation":""},{"arabic":"وَلِلرَّسُوۡلِ","transliteration":"","translation":""},{"arabic":"وَلِذِى","transliteration":"","translation":""},{"arabic":"الۡقُرۡبٰى","transliteration":"","translation":""},{"arabic":"وَالۡيَتٰمٰى","transliteration":"","translation":""},{"arabic":"وَالۡمَسٰكِيۡنِ","transliteration":"","translation":""},{"arabic":"وَابۡنِ","transliteration":"","translation":""},{"arabic":"السَّبِيۡلِۙ","transliteration":"","translation":""},{"arabic":"كَىۡ","transliteration":"","translation":""},{"arabic":"لَا","transliteration":"","translation":""},{"arabic":"يَكُوۡنَ","transliteration":"","translation":""},{"arabic":"دُوۡلَةًۢ","transliteration":"","translation":""},{"arabic":"بَيۡنَ","transliteration":"","translation":""},{"arabic":"الۡاَغۡنِيَآءِ","transliteration":"","translation":""},{"arabic":"مِنۡكُمۡ​ ؕ","transliteration":"","translation":""},{"arabic":"","transliteration":"","translation":""},{"arabic":"وَمَاۤ","transliteration":"","translation":""},{"arabic":"اٰتٰٮكُمُ","transliteration":"","translation":""},{"arabic":"الرَّسُوۡلُ","transliteration":"","translation":""},{"arabic":"فَخُذُوْهُ","transliteration":"","translation":""},{"arabic":"وَ","transliteration":"","translation":""},{"arabic":"مَا َنَهٰٮكُمۡ","transliteration":"","translation":""},{"arabic":"عَنۡهُ","transliteration":"","translation":""},{"arabic":"فَانْتَهُوۡا​ ۚ","transliteration":"","translation":""},{"arabic":"","transliteration":"","translation":""},{"arabic":"وَاتَّقُوا","transliteration":"","translation":""},{"arabic":"اللّٰهَ ​ؕ","transliteration":"","translation":""},{"arabic":"","transliteration":"","translation":""},{"arabic":"اِنَّ","transliteration":"","translation":""},{"arabic":"اللّٰهَ","transliteration":"","translation":""},{"arabic":"شَدِيۡدُ","transliteration":"","translation":""},{"arabic":"الۡعِقَابِ​ۘ","transliteration":"","translation":""}],"8":[{"arabic":"لِلۡفُقَرَآءِ","transliteration":"","translation":""},{"arabic":"الۡمُهٰجِرِيۡنَ","transliteration":"","translation":""},{"arabic":"الَّذِيۡنَ","transliteration":"","translation":""},{"arabic":"اُخۡرِجُوۡا","transliteration":"","translation":""},{"arabic":"مِنۡ","transliteration":"","translation":""},{"arabic":"دِيَارِهِمۡ","transliteration":"","translation":""},{"arabic":"وَاَمۡوَالِهِمۡ","transliteration":"","translation":""},{"arabic":"يَبۡتَغُوۡنَ","transliteration":"","translation":""},{"arabic":"فَضۡلًا","transliteration":"","translation":""},{"arabic":"مِّنَ","transliteration":"","translation":""},{"arabic":"اللّٰهِ","transliteration":"","translation":""},{"arabic":"وَرِضۡوَانًا","transliteration":"","translation":""},{"arabic":"وَّيَنۡصُرُوۡنَ","transliteration":"","translation":""},{"arabic":"اللّٰهَ","transliteration":"","translation":""},{"arabic":"وَرَسُوۡلَهٗ​ؕ","transliteration":"","translation":""},{"arabic":"","transliteration":"","translation":""},{"arabic":"اُولٰٓٮِٕكَ","transliteration":"","translation":""},{"arabic":"هُمُ","transliteration":"","translation":""},{"arabic":"الصّٰدِقُوۡنَ​ۚ","transliteration":"","translation":""}],"9":[{"arabic":"وَالَّذِيۡنَ","transliteration":"","translation":""},{"arabic":"تَبَوَّؤُ","transliteration":"","translation":""},{"arabic":"الدَّارَ","transliteration":"","translation":""},{"arabic":"وَالۡاِيۡمَانَ","transliteration":"","translation":""},{"arabic":"مِنۡ","transliteration":"","translation":""},{"arabic":"قَبۡلِهِمۡ","transliteration":"","translation":""},{"arabic":"يُحِبُّوۡنَ","transliteration":"","translation":""},{"arabic":"مَنۡ","transliteration":"","translation":""},{"arabic":"هَاجَرَ","transliteration":"","translation":""},{"arabic":"اِلَيۡهِمۡ","transliteration":"","translation":""},{"arabic":"وَلَا","transliteration":"","translation":""},{"arabic":"يَجِدُوۡنَ","transliteration":"","translation":""},{"arabic":"فِىۡ","transliteration":"","translation":""},{"arabic":"صُدُوۡرِهِمۡ","transliteration":"","translation":""},{"arabic":"حَاجَةً","transliteration":"","translation":""},{"arabic":"مِّمَّاۤ","transliteration":"","translation":""},{"arabic":"اُوۡتُوۡا","transliteration":"","translation":""},{"arabic":"وَيُـؤۡثِرُوۡنَ","transliteration":"","translation":""},{"arabic":"عَلٰٓى","transliteration":"","translation":""},{"arabic":"اَنۡفُسِهِمۡ","transliteration":"","translation":""},{"arabic":"وَلَوۡ","transliteration":"","translation":""},{"arabic":"كَانَ","transliteration":"","translation":""},{"arabic":"بِهِمۡ","transliteration":"","translation":""},{"arabic":"خَصَاصَةٌ ؕ","transliteration":"","translation":""},{"arabic":"","transliteration":"","translation":""},{"arabic":"وَمَنۡ","transliteration":"","translation":""},{"arabic":"يُّوۡقَ","transliteration":"","translation":""},{"arabic":"شُحَّ","transliteration":"","translation":""},{"arabic":"نَـفۡسِهٖ","transliteration":"","translation":""},{"arabic":"فَاُولٰٓٮِٕكَ","transliteration":"","translation":""},{"arabic":"هُمُ","transliteration":"","translation":""},{"arabic":"الۡمُفۡلِحُوۡنَ​ۚ","transliteration":"","translation":""}],"10":[{"arabic":"وَالَّذِيۡنَ","transliteration":"","translation":""},{"arabic":"جَآءُوۡ","transliteration":"","translation":""},{"arabic":"مِنۡۢ","transliteration":"","translation":""},{"arabic":"بَعۡدِهِمۡ","transliteration":"","translation":""},{"arabic":"يَقُوۡلُوۡنَ","transliteration":"","translation":""},{"arabic":"رَبَّنَا","transliteration":"","translation":""},{"arabic":"اغۡفِرۡ","transliteration":"","translation":""},{"arabic":"لَـنَا","transliteration":"","translation":""},{"arabic":"وَلِاِخۡوَانِنَا","transliteration":"","translation":""},{"arabic":"الَّذِيۡنَ","transliteration":"","translation":""},{"arabic":"سَبَقُوۡنَا","transliteration":"","translation":""},{"arabic":"بِالۡاِيۡمَانِ","transliteration":"","translation":""},{"arabic":"وَلَا","transliteration":"","translation":""},{"arabic":"تَجۡعَلۡ","transliteration":"","translation":""},{"arabic":"فِىۡ","transliteration":"","translation":""},{"arabic":"قُلُوۡبِنَا","transliteration":"","translation":""},{"arabic":"غِلًّا","transliteration":"","translation":""},{"arabic":"لِّلَّذِيۡنَ","transliteration":"","translation":""},{"arabic":"اٰمَنُوۡا","transliteration":"","translation":""},{"arabic":"رَبَّنَاۤ","transliteration":"","translation":""},{"arabic":"اِنَّكَ","transliteration":"","translation":""},{"arabic":"رَءُوۡفٌ","transliteration":"","translation":""},{"arabic":"رَّحِيۡمٌ","transliteration":"","translation":""}],"11":[{"arabic":"۞","transliteration":"","translation":""},{"arabic":"اَلَمۡ","transliteration":"","translation":""},{"arabic":"تَرَ","transliteration":"","translation":""},{"arabic":"اِلَى","transliteration":"","translation":""},{"arabic":"الَّذِيۡنَ","transliteration":"","translation":""},{"arabic":"نَافَقُوۡا","transliteration":"","translation":""},{"arabic":"يَقُوۡلُوۡنَ","transliteration":"","translation":""},{"arabic":"لِاِخۡوَانِهِمُ","transliteration":"","translation":""},{"arabic":"الَّذِيۡنَ","transliteration":"","translation":""},{"arabic":"كَفَرُوۡا","transliteration":"","translation":""},{"arabic":"مِنۡ","transliteration":"","translation":""},{"arabic":"اَهۡلِ","transliteration":"","translation":""},{"arabic":"الۡكِتٰبِ","transliteration":"","translation":""},{"arabic":"لَٮِٕنۡ","transliteration":"","translation":""},{"arabic":"اُخۡرِجۡتُمۡ","transliteration":"","translation":""},{"arabic":"لَنَخۡرُجَنَّ","transliteration":"","translation":""},{"arabic":"مَعَكُمۡ","transliteration":"","translation":""},{"arabic":"وَلَا","transliteration":"","translation":""},{"arabic":"نُطِيۡعُ","transliteration":"","translation":""},{"arabic":"فِيۡكُمۡ","transliteration":"","translation":""},{"arabic":"اَحَدًا","transliteration":"","translation":""},{"arabic":"اَبَدًاۙ","transliteration":"","translation":""},{"arabic":"وَّاِنۡ","transliteration":"","translation":""},{"arabic":"قُوۡتِلۡتُمۡ","transliteration":"","translation":""},{"arabic":"لَـنَـنۡصُرَنَّكُمۡ ؕ","transliteration":"","translation":""},{"arabic":"وَاللّٰهُ","transliteration":"","translation":""},{"arabic":"يَشۡهَدُ","transliteration":"","translation":""},{"arabic":"اِنَّهُمۡ","transliteration":"","translation":""},{"arabic":"لَـكٰذِبُوۡنَ","transliteration":"","translation":""}],"12":[{"arabic":"لَٮِٕنۡ","transliteration":"","translation":""},{"arabic":"اُخۡرِجُوۡا","transliteration":"","translation":""},{"arabic":"لَا","transliteration":"","translation":""},{"arabic":"يَخۡرُجُوۡنَ","transliteration":"","translation":""},{"arabic":"مَعَهُمۡ​ۚ","transliteration":"","translation":""},{"arabic":"وَلَٮِٕنۡ","transliteration":"","translation":""},{"arabic":"قُوۡتِلُوۡا","transliteration":"","translation":""},{"arabic":"لَا","transliteration":"","translation":""},{"arabic":"يَنۡصُرُوۡنَهُمۡ​ۚ","transliteration":"","translation":""},{"arabic":"وَلَٮِٕنۡ","transliteration":"","translation":""},{"arabic":"نَّصَرُوۡهُمۡ","transliteration":"","translation":""},{"arabic":"لَيُوَلُّنَّ","transliteration":"","translation":""},{"arabic":"الۡاَدۡبَارَ","transliteration":"","translation":""},{"arabic":"ثُمَّ","transliteration":"","translation":""},{"arabic":"لَا","transliteration":"","translation":""},{"arabic":"يُنۡصَرُوۡنَ","transliteration":"","translation":""}],"13":[{"arabic":"لَاَنۡتُمۡ","transliteration":"","translation":""},{"arabic":"اَشَدُّ","transliteration":"","translation":""},{"arabic":"رَهۡبَةً","transliteration":"","translation":""},{"arabic":"فِىۡ","transliteration":"","translation":""},{"arabic":"صُدُوۡرِهِمۡ","transliteration":"","translation":""},{"arabic":"مِّنَ","transliteration":"","translation":""},{"arabic":"اللّٰهِ​ؕ","transliteration":"","translation":""},{"arabic":"","transliteration":"","translation":""},{"arabic":"ذٰلِكَ","transliteration":"","translation":""},{"arabic":"بِاَنَّهُمۡ","transliteration":"","translation":""},{"arabic":"قَوۡمٌ","transliteration":"","translation":""},{"arabic":"لَّا","transliteration":"","translation":""},{"arabic":"يَفۡقَهُوۡنَ","transliteration":"","translation":""}],"14":[{"arabic":"لَا","transliteration":"","translation":""},{"arabic":"يُقَاتِلُوۡنَكُمۡ","transliteration":"","translation":""},{"arabic":"جَمِيۡعًا","transliteration":"","translation":""},{"arabic":"اِلَّا","transliteration":"","translation":""},{"arabic":"فِىۡ","transliteration":"","translation":""},{"arabic":"قُرًى","transliteration":"","translation":""},{"arabic":"مُّحَصَّنَةٍ","transliteration":"","translation":""},{"arabic":"اَوۡ","transliteration":"","translation":""},{"arabic":"مِنۡ","transliteration":"","translation":""},{"arabic":"وَّرَآءِ","transliteration":"","translation":""},{"arabic":"جُدُرٍؕ","transliteration":"","translation":""},{"arabic":"","transliteration":"","translation":""},{"arabic":"بَاۡسُهُمۡ","transliteration":"","translation":""},{"arabic":"بَيۡنَهُمۡ","transliteration":"","translation":""},{"arabic":"شَدِيۡدٌ ​ؕ","transliteration":"","translation":""},{"arabic":"","transliteration":"","translation":""},{"arabic":"تَحۡسَبُهُمۡ","transliteration":"","translation":""},{"arabic":"جَمِيۡعًا","transliteration":"","translation":""},{"arabic":"وَّقُلُوۡبُهُمۡ","transliteration":"","translation":""},{"arabic":"شَتّٰى​ؕ","transliteration":"","translation":""},{"arabic":"","transliteration":"","translation":""},{"arabic":"ذٰلِكَ","transliteration":"","translation":""},{"arabic":"بِاَنَّهُمۡ","transliteration":"","translation":""},{"arabic":"قَوۡمٌ","transliteration":"","translation":""},{"arabic":"لَّا","transliteration":"","translation":""},{"arabic":"يَعۡقِلُوۡنَ​ۚ","transliteration":"","translation":""}],"15":[{"arabic":"كَمَثَلِ","transliteration":"","translation":""},{"arabic":"الَّذِيۡنَ","transliteration":"","translation":""},{"arabic":"مِنۡ","transliteration":"","translation":""},{"arabic":"قَبۡلِهِمۡ","transliteration":"","translation":""},{"arabic":"قَرِيۡبًا​","transliteration":"","translation":""},{"arabic":"","transliteration":"","translation":""},{"arabic":"ذَاقُوۡا","transliteration":"","translation":""},{"arabic":"وَبَالَ","transliteration":"","translation":""},{"arabic":"اَمۡرِهِمۡ​ۚ","transliteration":"","translation":""},{"arabic":"وَلَهُمۡ","transliteration":"","translation":""},{"arabic":"عَذَابٌ","transliteration":"","translation":""},{"arabic":"اَلِيۡمٌ​ۚ","transliteration":"","translation":""}],"16":[{"arabic":"كَمَثَلِ","transliteration":"","translation":""},{"arabic":"الشَّيۡطٰنِ","transliteration":"","translation":""},{"arabic":"اِذۡ","transliteration":"","translation":""},{"arabic":"قَالَ","transliteration":"","translation":""},{"arabic":"لِلۡاِنۡسَانِ","transliteration":"","translation":""},{"arabic":"اكۡفُرۡ​ۚ","transliteration":"","translation":""},{"arabic":"فَلَمَّا","transliteration":"","translation":""},{"arabic":"كَفَرَ","transliteration":"","translation":""},{"arabic":"قَالَ","transliteration":"","translation":""},{"arabic":"اِنِّىۡ","transliteration":"","translation":""},{"arabic":"بَرِىۡٓءٌ","transliteration":"","translation":""},{"arabic":"مِّنۡكَ","transliteration":"","translation":""},{"arabic":"اِنِّىۡۤ","transliteration":"","translation":""},{"arabic":"اَخَافُ","transliteration":"","translation":""},{"arabic":"اللّٰهَ","transliteration":"","translation":""},{"arabic":"رَبَّ","transliteration":"","translation":""},{"arabic":"الۡعٰلَمِيۡنَ","transliteration":"","translation":""}],"17":[{"arabic":"فَكَانَ","transliteration":"","translation":""},{"arabic":"عَاقِبَتَهُمَاۤ","transliteration":"","translation":""},{"arabic":"اَنَّهُمَا","transliteration":"","translation":""},{"arabic":"فِى","transliteration":"","translation":""},{"arabic":"النَّارِ","transliteration":"","translation":""},{"arabic":"خَالِدَيۡنِ","transliteration":"","translation":""},{"arabic":"فِيۡهَا​ ؕ","transliteration":"","translation":""},{"arabic":"","transliteration":"","translation":""},{"arabic":"وَذٰ لِكَ","transliteration":"","translation":""},{"arabic":"جَزٰٓؤُا","transliteration":"","translation":""},{"arabic":"الظّٰلِمِيۡن","transliteration":"","translation":""}],"18":[{"arabic":"يٰۤاَيُّهَا","transliteration":"","translation":""},{"arabic":"الَّذِيۡنَ","transliteration":"","translation":""},{"arabic":"اٰمَنُوۡا","transliteration":"","translation":""},{"arabic":"اتَّقُوا","transliteration":"","translation":""},{"arabic":"اللّٰهَ","transliteration":"","translation":""},{"arabic":"وَلۡتَـنۡظُرۡ","transliteration":"","translation":""},{"arabic":"نَـفۡسٌ","transliteration":"","translation":""},{"arabic":"مَّا","transliteration":"","translation":""},{"arabic":"قَدَّمَتۡ","transliteration":"","translation":""},{"arabic":"لِغَدٍ​ ۚ","transliteration":"","translation":""},{"arabic":"","transliteration":"","translation":""},{"arabic":"وَاتَّقُوا","transliteration":"","translation":""},{"arabic":"اللّٰهَ​ؕ","transliteration":"","translation":""},{"arabic":"","transliteration":"","translation":""},{"arabic":"اِنَّ","transliteration":"","translation":""},{"arabic":"اللّٰهَ","transliteration":"","translation":""},{"arabic":"خَبِيۡرٌۢ","transliteration":"","translation":""},{"arabic":"بِمَا","transliteration":"","translation":""},{"arabic":"تَعۡمَلُوۡنَ ","transliteration":"","translation":""}],"19":[{"arabic":"وَلَا","transliteration":"","translation":""},{"arabic":"تَكُوۡنُوۡا","transliteration":"","translation":""},{"arabic":"كَالَّذِيۡنَ","transliteration":"","translation":""},{"arabic":"نَسُوا","transliteration":"","translation":""},{"arabic":"اللّٰهَ","transliteration":"","translation":""},{"arabic":"فَاَنۡسٰٮهُمۡ","transliteration":"","translation":""},{"arabic":"اَنۡفُسَهُمۡ​ؕ","transliteration":"","translation":""},{"arabic":"","transliteration":"","translation":""},{"arabic":"اُولٰٓٮِٕكَ","transliteration":"","translation":""},{"arabic":"هُمُ","transliteration":"","translation":""},{"arabic":"الۡفٰسِقُوۡنَ","transliteration":"","translation":""}],"20":[{"arabic":"لَا","transliteration":"","translation":""},{"arabic":"يَسۡتَوِىۡۤ","transliteration":"","translation":""},{"arabic":"اَصۡحٰبُ","transliteration":"","translation":""},{"arabic":"النَّارِ","transliteration":"","translation":""},{"arabic":"وَاَصۡحٰبُ","transliteration":"","translation":""},{"arabic":"الۡجَـنَّةِ​ؕ","transliteration":"","translation":""},{"arabic":"","transliteration":"","translation":""},{"arabic":"اَصۡحٰبُ","transliteration":"","translation":""},{"arabic":"الۡجَـنَّةِ","transliteration":"","translation":""},{"arabic":"هُمُ","transliteration":"","translation":""},{"arabic":"الۡفَآٮِٕزُوۡنَ","transliteration":"","translation":""}],"21":[{"arabic":"لَوۡ","transliteration":"","translation":""},{"arabic":"اَنۡزَلۡنَا","transliteration":"","translation":""},{"arabic":"هٰذَا","transliteration":"","translation":""},{"arabic":"الۡقُرۡاٰنَ","transliteration":"","translation":""},{"arabic":"عَلٰى","transliteration":"","translation":""},{"arabic":"جَبَلٍ","transliteration":"","translation":""},{"arabic":"لَّرَاَيۡتَهٗ","transliteration":"","translation":""},{"arabic":"خَاشِعًا","transliteration":"","translation":""},{"arabic":"مُّتَصَدِّعًا","transliteration":"","translation":""},{"arabic":"مِّنۡ","transliteration":"","translation":""},{"arabic":"خَشۡيَةِ","transliteration":"","translation":""},{"arabic":"اللّٰهِ​ؕ","transliteration":"","translation":""},{"arabic":"","transliteration":"","translation":""},{"arabic":"وَتِلۡكَ","transliteration":"","translation":""},{"arabic":"الۡاَمۡثَالُ","transliteration":"","translation":""},{"arabic":"نَضۡرِبُهَا","transliteration":"","translation":""},{"arabic":"لِلنَّاسِ","transliteration":"","translation":""},{"arabic":"لَعَلَّهُمۡ","transliteration":"","translation":""},{"arabic":"يَتَفَكَّرُوۡنَ","transliteration":"","translation":""}],"22":[{"arabic":"هُوَ","transliteration":"","translation":""},{"arabic":"اللّٰهُ","transliteration":"","translation":""},{"arabic":"الَّذِىۡ","transliteration":"","translation":""},{"arabic":"لَاۤ","transliteration":"","translation":""},{"arabic":"اِلٰهَ","transliteration":"","translation":""},{"arabic":"اِلَّا","transliteration":"","translation":""},{"arabic":"هُوَ​ ۚ","transliteration":"","translation":""},{"arabic":"","transliteration":"","translation":""},{"arabic":"عٰلِمُ","transliteration":"","translation":""},{"arabic":"الۡغَيۡبِ","transliteration":"","translation":""},{"arabic":"وَالشَّهَادَةِ​ ۚ","transliteration":"","translation":""},{"arabic":"","transliteration":"","translation":""},{"arabic":"هُوَ","transliteration":"","translation":""},{"arabic":"الرَّحۡمٰنُ","transliteration":"","translation":""},{"arabic":"الرَّحِيۡمُ","transliteration":"","translation":""}],"23":[{"arabic":"هُوَ","transliteration":"","translation":""},{"arabic":"اللّٰهُ","transliteration":"","translation":""},{"arabic":"الَّذِىۡ","transliteration":"","translation":""},{"arabic":"لَاۤ","transliteration":"","translation":""},{"arabic":"اِلٰهَ","transliteration":"","translation":""},{"arabic":"اِلَّا","transliteration":"","translation":""},{"arabic":"هُوَ​ۚ","transliteration":"","translation":""},{"arabic":"اَلۡمَلِكُ","transliteration":"","translation":""},{"arabic":"الۡقُدُّوۡسُ","transliteration":"","translation":""},{"arabic":"السَّلٰمُ","transliteration":"","translation":""},{"arabic":"الۡمُؤۡمِنُ","transliteration":"","translation":""},{"arabic":"الۡمُهَيۡمِنُ","transliteration":"","translation":""},{"arabic":"الۡعَزِيۡزُ","transliteration":"","translation":""},{"arabic":"الۡجَـبَّارُ","transliteration":"","translation":""},{"arabic":"الۡمُتَكَبِّرُ​ؕ","transliteration":"","translation":""},{"arabic":"","transliteration":"","translation":""},{"arabic":"سُبۡحٰنَ","transliteration":"","translation":""},{"arabic":"اللّٰهِ","transliteration":"","translation":""},{"arabic":"عَمَّا","transliteration":"","translation":""},{"arabic":"يُشۡرِكُوۡنَ","transliteration":"","translation":""}],"24":[{"arabic":"هُوَ","transliteration":"","translation":""},{"arabic":"اللّٰهُ","transliteration":"","translation":""},{"arabic":"الۡخَـالِـقُ","transliteration":"","translation":""},{"arabic":"الۡبَارِئُ","transliteration":"","translation":""},{"arabic":"الۡمُصَوِّرُ​","transliteration":"","translation":""},{"arabic":"","transliteration":"","translation":""},{"arabic":"لَـهُ","transliteration":"","translation":""},{"arabic":"الۡاَسۡمَآءُ","transliteration":"","translation":""},{"arabic":"الۡحُسۡنٰى​ؕ","transliteration":"","translation":""},{"arabic":"","transliteration":"","translation":""},{"arabic":"يُسَبِّحُ","transliteration":"","translation":""},{"arabic":"لَهٗ","transliteration":"","translation":""},{"arabic":"مَا","transliteration":"","translation":""},{"arabic":"فِى","transliteration":"","translation":""},{"arabic":"السَّمٰوٰتِ","transliteration":"","translation":""},{"arabic":"وَالۡاَرۡضِ​ۚ","transliteration":"","translation":""},{"arabic":"","transliteration":"","translation":""},{"arabic":"وَهُوَ","transliteration":"","translation":""},{"arabic":"الۡعَزِيۡزُ","transliteration":"","translation":""},{"arabic":"الۡحَكِيۡمُ ","transliteration":"","translation":""}]}