{"1":[{"arabic":"لَاۤ","transliteration":"","translation":""},{"arabic":"اُقۡسِمُ","transliteration":"","translation":""},{"arabic":"بِهٰذَا","transliteration":"","translation":""},{"arabic":"الۡبَلَدِۙ","transliteration":"","translation":""}],"2":[{"arabic":"وَاَنۡتَ","transliteration":"","translation":""},{"arabic":"حِلٌّ ۢ","transliteration":"","translation":""},{"arabic":"بِهٰذَا","transliteration":"","translation":""},{"arabic":"الۡبَلَدِۙ","transliteration":"","translation":""}],"3":[{"arabic":"وَوَالِدٍ","transliteration":"","translation":""},{"arabic":"وَّمَا","transliteration":"","translation":""},{"arabic":"وَلَدَ ۙ","transliteration":"","translation":""}],"4":[{"arabic":"لَقَدۡ","transliteration":"","translation":""},{"arabic":"خَلَقۡنَا","transliteration":"","translation":""},{"arabic":"الۡاِنۡسَانَ","transliteration":"","translation":""},{"arabic":"فِىۡ","transliteration":"","translation":""},{"arabic":"كَبَدٍؕ","transliteration":"","translation":""}],"5":[{"arabic":"اَيَحۡسَبُ","transliteration":"","translation":""},{"arabic":"اَنۡ","transliteration":"","translation":""},{"arabic":"لَّنۡ","transliteration":"","translation":""},{"arabic":"يَّقۡدِرَ","transliteration":"","translation":""},{"arabic":"عَلَيۡهِ","transliteration":"","translation":""},{"arabic":"اَحَدٌ​ ۘ","transliteration":"","translation":""}],"6":[{"arabic":"يَقُوۡلُ","transliteration":"","translation":""},{"arabic":"اَهۡلَكۡتُ","transliteration":"","translation":""},{"arabic":"مَالًا","transliteration":"","translation":""},{"arabic":"لُّبَدًا ؕ","transliteration":"","translation":""}],"7":[{"arabic":"اَيَحۡسَبُ","transliteration":"","translation":""},{"arabic":"اَنۡ","transliteration":"","translation":""},{"arabic":"لَّمۡ","transliteration":"","translation":""},{"arabic":"يَرَهٗۤ","transliteration":"","translation":""},{"arabic":"اَحَدٌ ؕ","transliteration":"","translation":""}],"8":[{"arabic":"اَلَمۡ","transliteration":"","translation":""},{"arabic":"نَجۡعَلۡ","transliteration":"","translation":""},{"arabic":"لَّهٗ","transliteration":"","translation":""},{"arabic":"عَيۡنَيۡنِۙ","transliteration":"","translation":""}],"9":[{"arabic":"وَلِسَانًا","transliteration":"","translation":""},{"arabic":"وَّشَفَتَيۡنِۙ","transliteration":"","translation":""}],"10":[{"arabic":"وَهَدَيۡنٰهُ","transliteration":"","translation":""},{"arabic":"النَّجۡدَيۡنِ​ۚ","transliteration":"","translation":""}],"11":[{"arabic":"فَلَا","transliteration":"","translation":""},{"arabic":"اقۡتَحَمَ","transliteration":"","translation":""},{"arabic":"الۡعَقَبَةَ ۖ","transliteration":"","translation":""}],"12":[{"arabic":"وَمَاۤ","transliteration":"","translation":""},{"arabic":"اَدۡرٰٮكَ","transliteration":"","translation":""},{"arabic":"مَا","transliteration":"","translation":""},{"arabic":"الۡعَقَبَةُ ؕ","transliteration":"","translation":""}],"13":[{"arabic":"فَكُّ","transliteration":"","translation":""},{"arabic":"رَقَبَةٍ ۙ","transliteration":"","translation":""}],"14":[{"arabic":"اَوۡ","transliteration":"","translation":""},{"arabic":"اِطۡعٰمٌ","transliteration":"","translation":""},{"arabic":"فِىۡ","transliteration":"","translation":""},{"arabic":"يَوۡمٍ","transliteration":"","translation":""},{"arabic":"ذِىۡ","transliteration":"","translation":""},{"arabic":"مَسۡغَبَةٍ ۙ","transliteration":"","translation":""}],"15":[{"arabic":"يَّتِيۡمًا","transliteration":"","translation":""},{"arabic":"ذَا","transliteration":"","translation":""},{"arabic":"مَقۡرَبَةٍ ۙ","transliteration":"","translation":""}],"16":[{"arabic":"اَوۡ","transliteration":"","translation":""},{"arabic":"مِسۡكِيۡنًا","transliteration":"","translation":""},{"arabic":"ذَا","transliteration":"","translation":""},{"arabic":"مَتۡرَبَةٍ ؕ","transliteration":"","translation":""}],"17":[{"arabic":"ثُمَّ","transliteration":"","translation":""},{"arabic":"كَانَ","transliteration":"","translation":""},{"arabic":"مِنَ","transliteration":"","translation":""},{"arabic":"الَّذِيۡنَ","transliteration":"","translation":""},{"arabic":"اٰمَنُوۡا","transliteration":"","translation":""},{"arabic":"وَتَوَاصَوۡا","transliteration":"","translation":""},{"arabic":"بِالصَّبۡرِ","transliteration":"","translation":""},{"arabic":"وَتَوَاصَوۡا","transliteration":"","translation":""},{"arabic":"بِالۡمَرۡحَمَةِ ؕ","transliteration":"","translation":""}],"18":[{"arabic":"اُولٰٓٮِٕكَ","transliteration":"","translation":""},{"arabic":"اَصۡحٰبُ","transliteration":"","translation":""},{"arabic":"الۡمَيۡمَنَةِ ؕ","transliteration":"","translation":""}],"19":[{"arabic":"وَالَّذِيۡنَ","transliteration":"","translation":""},{"arabic":"كَفَرُوۡا","transliteration":"","translation":""},{"arabic":"بِاٰيٰتِنَا","transliteration":"","translation":""},{"arabic":"هُمۡ","transliteration":"","translation":""},{"arabic":"اَصۡحٰبُ","transliteration":"","translation":""},{"arabic":"الۡمَشۡـَٔـمَةِ ؕ","transliteration":"","translation":""}],"20":[{"arabic":"عَلَيۡهِمۡ","transliteration":"","translation":""},{"arabic":"نَارٌ","transliteration":"","translation":""},{"arabic":"مُّؤۡصَدَةٌ","transliteration":"","translation":""}]}